setup.py
ppaquette_gym_doom/__init__.py
ppaquette_gym_doom/doom_basic.py
ppaquette_gym_doom/doom_corridor.py
ppaquette_gym_doom/doom_deathmatch.py
ppaquette_gym_doom/doom_defend_center.py
ppaquette_gym_doom/doom_defend_line.py
ppaquette_gym_doom/doom_env.py
ppaquette_gym_doom/doom_health_gathering.py
ppaquette_gym_doom/doom_my_way_home.py
ppaquette_gym_doom/doom_predict_position.py
ppaquette_gym_doom/doom_take_cover.py
ppaquette_gym_doom/meta_doom.py
ppaquette_gym_doom/package_info.py
ppaquette_gym_doom.egg-info/PKG-INFO
ppaquette_gym_doom.egg-info/SOURCES.txt
ppaquette_gym_doom.egg-info/dependency_links.txt
ppaquette_gym_doom.egg-info/not-zip-safe
ppaquette_gym_doom.egg-info/requires.txt
ppaquette_gym_doom.egg-info/top_level.txt
ppaquette_gym_doom/assets/basic.cfg
ppaquette_gym_doom/assets/deadly_corridor.cfg
ppaquette_gym_doom/assets/deathmatch.cfg
ppaquette_gym_doom/assets/defend_the_center.cfg
ppaquette_gym_doom/assets/defend_the_line.cfg
ppaquette_gym_doom/assets/health_gathering.cfg
ppaquette_gym_doom/assets/my_way_home.cfg
ppaquette_gym_doom/assets/predict_position.cfg
ppaquette_gym_doom/assets/take_cover.cfg
ppaquette_gym_doom/wrappers/__init__.py
ppaquette_gym_doom/wrappers/action_space.py
ppaquette_gym_doom/wrappers/control.py
ppaquette_gym_doom/wrappers/custom_game.py
ppaquette_gym_doom/wrappers/multi_discrete.py
ppaquette_gym_doom/wrappers/observation_space.py