Metadata-Version: 1.0
Name: ppaquette-gym-doom
Version: 0.0.5
Summary: Gym User Env - 9 Doom levels based on VizDoom
Home-page: https://github.com/ppaquette/gym-doom
Author: Philip Paquette
Author-email: pcpaquette@gmail.com
License: MIT License
Platform: UNKNOWN
